LICENSE
MANIFEST.in
README.md
Tool.py
setup.py
lzbTestLib/__init__.py
lzbTestLib/lzb_print_lib.py
lzbTestLib.egg-info/PKG-INFO
lzbTestLib.egg-info/SOURCES.txt
lzbTestLib.egg-info/dependency_links.txt
lzbTestLib.egg-info/top_level.txt