Metadata-Version: 1.0
Name: lzbTestLib
Version: 0.0.3
Summary: 这是刘子彬的python测试包
Home-page: https://gitee.com/zibincode/PythonStudyDemo.git
Author: lzb
Author-email: 1835064412@qq.com
License: UNKNOWN
Platform: UNKNOWN
